setup.py
ouchdb/__init__.py
ouchdb/cli.py
ouchdb/database.py
ouchdb/engine.py
ouchdb/http.py
ouchdb/schema.py
ouchdb/server.py
ouchdb/version.py
ouchdb/webapp.py
ouchdb.egg-info/PKG-INFO
ouchdb.egg-info/SOURCES.txt
ouchdb.egg-info/dependency_links.txt
ouchdb.egg-info/requires.txt
ouchdb.egg-info/top_level.txt
ouchdb/tests/__init__.py
ouchdb/tests/test_engine.py