Metadata-Version: 1.0
Name: ouchdb
Version: 0.1
Summary: OuchDB is an implementation of CouchDB API on relational databases
Home-page: UNKNOWN
Author: Anand Chitipothu
Author-email: anandology@gmail.com
License: Apache License, Version 2.0
Platform: any
